{
  "positions": {
    "pinky": [
      {
        "x": 58,
        "y": 469.3415841584158
      },
      {
        "x": 97,
        "y": 591.8688118811881
      },
      {
        "x": 115,
        "y": 742.4319306930693
      },
      {
        "x": 102,
        "y": 775.6596534653464
      },
      {
        "x": 62,
        "y": 392.5024752475247
      }
    ],
    "ring": [
      {
        "x": 219,
        "y": 300.0878712871287
      },
      {
        "x": 212,
        "y": 427.80693069306926
      },
      {
        "x": 266,
        "y": 618.8663366336633
      },
      {
        "x": 240,
        "y": 750.7388613861385
      }
    ],
    "middle": [
      {
        "x": 342,
        "y": 231.30834340991538
      },
      {
        "x": 385,
        "y": 379.0037128712871
      },
      {
        "x": 360,
        "y": 551.3725247524752
      },
      {
        "x": 377,
        "y": 684.2834158415841
      },
      {
        "x": 381,
        "y": 767.3527227722772
      }
    ],
    "index": [
      {
        "x": 593,
        "y": 280.35891089108907
      },
      {
        "x": 557,
        "y": 458.95792079207916
      },
      {
        "x": 542,
        "y": 614.7128712871287
      },
      {
        "x": 514,
        "y": 708.1658415841583
      }
    ],
    "index_far": [
      {
        "x": 740,
        "y": 447.5358910891089
      },
      {
        "x": 722,
        "y": 482.8403465346534
      },
      {
        "x": 668,
        "y": 626.1349009900989
      },
      {
        "x": 660,
        "y": 691.5519801980198
      },
      {
        "x": 632,
        "y": 765.2759900990098
      },
      {
        "x": 590,
        "y": 796.4269801980197
      }
    ],
    "thumb": [
      {
        "x": 692.6494066882416,
        "y": 893.2143028557715
      },
      {
        "x": 750.1618122977346,
        "y": 989.4874010079194
      },
      {
        "x": 832.6796116504854,
        "y": 1040.749700023998
      },
      {
        "x": 592.6278317152103,
        "y": 843.2023038156948
      },
      {
        "x": 872.6882416396979,
        "y": 1040.749700023998
      },
      {
        "x": 897.6936353829558,
        "y": 1040.749700023998
      }
    ]
  },
  "calibratedPPM": 5.285714285714286,
  "canvasWidth": 2318,
  "canvasHeight": 1042
}